awkward/__init__.py
awkward/_attrs.py
awkward/_behavior.py
awkward/_broadcasting.py
awkward/_categorical.py
awkward/_dispatch.py
awkward/_do.py
awkward/_errors.py
awkward/_ext.py
awkward/_kernels.py
awkward/_layout.py
awkward/_lookup.py
awkward/_namedaxis.py
awkward/_operators.py
awkward/_parameters.py
awkward/_pickle.py
awkward/_prettyprint.py
awkward/_reducers.py
awkward/_regularize.py
awkward/_singleton.py
awkward/_slicing.py
awkward/_typetracer.py
awkward/_typing.py
awkward/_util.py
awkward/_v2.py
awkward/_version.py
awkward/builder.py
awkward/cppyy.py
awkward/errors.py
awkward/forth.py
awkward/highlevel.py
awkward/index.py
awkward/jax.py
awkward/prettyprint.py
awkward/record.py
awkward/typetracer.py
awkward/_backends/__init__.py
awkward/_backends/backend.py
awkward/_backends/cupy.py
awkward/_backends/dispatch.py
awkward/_backends/jax.py
awkward/_backends/numpy.py
awkward/_backends/typetracer.py
awkward/_connect/__init__.py
awkward/_connect/avro.py
awkward/_connect/cling.py
awkward/_connect/dlpack.py
awkward/_connect/hist.py
awkward/_connect/numexpr.py
awkward/_connect/numpy.py
awkward/_connect/cuda/__init__.py
awkward/_connect/cuda/_kernel_signatures.py
awkward/_connect/cuda/cuda_kernels/awkward_BitMaskedArray_to_ByteMaskedArray.cu
awkward/_connect/cuda/cuda_kernels/awkward_BitMaskedArray_to_IndexedOptionArray.cu
awkward/_connect/cuda/cuda_kernels/awkward_ByteMaskedArray_getitem_nextcarry.cu
awkward/_connect/cuda/cuda_kernels/awkward_ByteMaskedArray_getitem_nextcarry_outindex.cu
awkward/_connect/cuda/cuda_kernels/awkward_ByteMaskedArray_numnull.cu
awkward/_connect/cuda/cuda_kernels/awkward_ByteMaskedArray_overlay_mask.cu
awkward/_connect/cuda/cuda_kernels/awkward_ByteMaskedArray_reduce_next_64.cu
awkward/_connect/cuda/cuda_kernels/awkward_ByteMaskedArray_reduce_next_nonlocal_nextshifts_64.cu
awkward/_connect/cuda/cuda_kernels/awkward_ByteMaskedArray_reduce_next_nonlocal_nextshifts_fromshifts_64.cu
awkward-2.8.8.dist-info/METADATA
awkward-2.8.8.dist-info/WHEEL
awkward-2.8.8.dist-info/entry_points.txt
awkward-2.8.8.dist-info/licenses/LICENSE
awkward-2.8.8.dist-info/RECORD
