Metadata-Version: 2.4
Name: awkward
Version: 2.8.8
Summary: Manipulate JSON-like data with NumPy-like idioms.
Project-URL: Bug Tracker, https://github.com/scikit-hep/awkward-1.0/issues
Project-URL: Chat, https://gitter.im/Scikit-HEP/awkward-array
Project-URL: Discussions, https://github.com/scikit-hep/awkward-1.0/discussions
Project-URL: Documentation, https://awkward-array.org
Project-URL: Homepage, https://github.com/scikit-hep/awkward-1.0
Project-URL: Releases, https://github.com/scikit-hep/awkward-1.0/releases
Project-URL: Source Code, https://github.com/scikit-hep/awkward-1.0
Author-email: Jim Pivarski <jpivarski@gmail.com>
License-Expression: BSD-3-Clause
License-File: LICENSE
Classifier: Development Status :: 5 - Production/Stable
Classifier: Intended Audience :: Developers
Classifier: Intended Audience :: Information Technology
Classifier: Intended Audience :: Science/Research
Classifier: Operating System :: MacOS :: MacOS X
Classifier: Operating System :: Microsoft :: Windows
Classifier: Operating System :: POSIX :: Linux
Classifier: Operating System :: Unix
Classifier: Programming Language :: Python
Classifier: Programming Language :: Python :: 3
Classifier: Programming Language :: Python :: 3 :: Only
Classifier: Programming Language :: Python :: 3.9
Classifier: Programming Language :: Python :: 3.10
Classifier: Programming Language :: Python :: 3.11
Classifier: Programming Language :: Python :: 3.12
Classifier: Programming Language :: Python :: 3.13
Classifier: Programming Language :: Python :: 3.14
Classifier: Programming Language :: Python :: Free Threading
Classifier: Programming Language :: Python :: Free Threading :: 3 - Stable
Classifier: Topic :: Scientific/Engineering
Classifier: Topic :: Scientific/Engineering :: Information Analysis
Classifier: Topic :: Scientific/Engineering :: Mathematics
Classifier: Topic :: Scientific/Engineering :: Physics
Classifier: Topic :: Software Development
Classifier: Topic :: Utilities
Requires-Python: >=3.9
Requires-Dist: awkward-cpp==49
Requires-Dist: fsspec>=2022.11.0
Requires-Dist: importlib-metadata>=4.13.0; python_version < '3.12'
Requires-Dist: numpy>=1.18.0
Requires-Dist: packaging
Requires-Dist: typing-extensions>=4.1.0; python_version < '3.11'
